{"is_source_file": true, "format": "JavaScript (JSX)", "description": "This file defines the routing structure for a React-based web application, specifying public and protected routes, route redirections, placeholder components, and guards for authentication and role-based access control.", "external_files": ["../pages/SignIn", "../pages/SignUp", "../pages/ForgotPassword", "../pages/VerifyEmail", "../pages/Profile", "../components/guards/AuthGuard", "../components/guards/AuthGuard", "../components/ui/Card"], "external_methods": ["React", "Routes", "Route", "Navigate"], "published": ["RoutesRoot"], "classes": [], "methods": [{"name": "Placeholder", "description": "Functional component rendering a placeholder UI inside a Card component, displaying a title and optional description."}, {"name": "RoutesRoot()", "description": "Main exported function defining all application routes, including public, authenticated, role-protected, and fallback routes.", "scope": "", "scopeKind": ""}], "calls": ["React", "Routes", "Route", "Navigate", "Placeholder", "SignIn", "SignUp", "ForgotPassword", "VerifyEmail", "Profile", "AuthGuard", "RoleGuard"], "search-terms": ["ReactRouter", "Route definitions", "AuthGuard", "RoleGuard", "public routes", "protected routes", "navigation", "placeholders", "React components"], "state": 2, "file_id": 23, "knowledge_revision": 97, "git_revision": "3bdf6b0c8aab3cf27c34ceb5aa9a13a5b5907552", "revision_history": [{"51": ""}, {"68": "5d33ce233e4af3de81e89141a3a27119a4d9882c"}, {"97": "3bdf6b0c8aab3cf27c34ceb5aa9a13a5b5907552"}], "ctags": [{"_type": "tag", "name": "Placeholder", "path": "/home/kavia/workspace/code-generation/immersive-learning-platform-253126-253136/lms_frontend/src/router/Routes.jsx", "pattern": "/^const Placeholder = ({ title, desc }) => ($/", "language": "JavaScript", "kind": "constant"}, {"_type": "tag", "name": "RoutesRoot", "path": "/home/kavia/workspace/code-generation/immersive-learning-platform-253126-253136/lms_frontend/src/router/Routes.jsx", "pattern": "/^export function RoutesRoot() {$/", "language": "JavaScript", "kind": "function", "signature": "()"}, {"_type": "tag", "name": "title", "path": "/home/kavia/workspace/code-generation/immersive-learning-platform-253126-253136/lms_frontend/src/router/Routes.jsx", "pattern": "/^const Placeholder = ({ title, desc }) => ($/", "language": "JavaScript", "kind": "field", "scope": "Placeholder", "scopeKind": "class"}], "hash": "6c9f729659297ad7da0ba406708b2960", "format-version": 4, "code-base-name": "lms_frontend", "filename": "lms_frontend/src/router/Routes.jsx", "fields": [{"name": "const Placeholder = ({ title, desc }) => (", "scope": "Placeholder", "scopeKind": "class", "description": "unavailable"}]}